<?xml version="1.0" encoding="UTF-8" standalone="yes"?>
<root xmlns:xsi="http://www.w3.org/2001/XMLSchema-instance">
	<T>
		<Id>1001</Id>
		<awardId>1708</awardId>
		<targetNum>1</targetNum>
		<targetLv>0</targetLv>
		<note>填写邀请人即可获得奖励</note>
	</T>
	<T>
		<Id>1002</Id>
		<awardId>1106</awardId>
		<targetNum>1</targetNum>
		<targetLv>20</targetLv>
		<note>邀请1名好友等级达到20级</note>
	</T>
	<T>
		<Id>1003</Id>
		<awardId>1047</awardId>
		<targetNum>5</targetNum>
		<targetLv>20</targetLv>
		<note>邀请5名好友等级达到20级</note>
	</T>
	<T>
		<Id>1004</Id>
		<awardId>1104</awardId>
		<targetNum>1</targetNum>
		<targetLv>40</targetLv>
		<note>邀请1名好友等级达到40级</note>
	</T>
	<T>
		<Id>1005</Id>
		<awardId>60039</awardId>
		<targetNum>3</targetNum>
		<targetLv>40</targetLv>
		<note>邀请3名好友等级达到40级</note>
	</T>
	<T>
		<Id>1006</Id>
		<awardId>1100</awardId>
		<targetNum>1</targetNum>
		<targetLv>60</targetLv>
		<note>邀请1名好友等级达到60级</note>
	</T>
	<T>
		<Id>1007</Id>
		<awardId>60002</awardId>
		<targetNum>3</targetNum>
		<targetLv>60</targetLv>
		<note>邀请3名好友等级达到60级</note>
	</T>
</root>