<?xml version="1.0" encoding="UTF-8" standalone="yes"?>
<root xmlns:xsi="http://www.w3.org/2001/XMLSchema-instance">
	<T>
		<Id>1</Id>
		<quality>1</quality>
		<series>1</series>
		<name>白色一阶</name>
		<goods>1030</goods>
		<value>3</value>
		<resolveGoods>1000,1030,0,1</resolveGoods>
		<coin>2,200,300</coin>
	</T>
	<T>
		<Id>2</Id>
		<quality>2</quality>
		<series>1</series>
		<name>绿色一阶</name>
		<goods>1030</goods>
		<value>6</value>
		<resolveGoods>1000,1030,0,1</resolveGoods>
		<coin>2,200,300</coin>
	</T>
	<T>
		<Id>3</Id>
		<quality>3</quality>
		<series>1</series>
		<name>蓝色一阶</name>
		<goods>1030</goods>
		<value>10</value>
		<resolveGoods>1000,1030,0,1</resolveGoods>
		<coin>2,400,600</coin>
	</T>
	<T>
		<Id>4</Id>
		<quality>4</quality>
		<series>1</series>
		<name>紫色一阶</name>
		<goods>1030</goods>
		<value>15</value>
		<resolveGoods>1000,1030,0,1</resolveGoods>
		<coin>2,600,900</coin>
	</T>
	<T>
		<Id>5</Id>
		<quality>5</quality>
		<series>1</series>
		<name>橙色一阶</name>
		<goods>1030</goods>
		<value>30</value>
		<resolveGoods>1000,1030,0,1</resolveGoods>
		<coin>2,1000,1500</coin>
	</T>
	<T>
		<Id>6</Id>
		<quality>6</quality>
		<series>1</series>
		<name>金色一阶</name>
		<goods>1030</goods>
		<value>50</value>
		<resolveGoods>1000,1030,0,1</resolveGoods>
		<coin>2,1600,2400</coin>
	</T>
	<T>
		<Id>7</Id>
		<quality>7</quality>
		<series>1</series>
		<name>粉色一阶</name>
		<goods>1030</goods>
		<value>90</value>
		<resolveGoods>1000,1030,0,1</resolveGoods>
		<coin>2,2000,3000</coin>
	</T>
	<T>
		<Id>8</Id>
		<quality>8</quality>
		<series>1</series>
		<name>红色一阶</name>
		<goods>1030</goods>
		<value>155</value>
		<resolveGoods>1000,1030,0,1</resolveGoods>
		<coin>2,2400,3600</coin>
	</T>
	<T>
		<Id>9</Id>
		<quality>1</quality>
		<series>2</series>
		<name>白色二阶</name>
		<goods>1030</goods>
		<value>5</value>
		<resolveGoods>1000,1030,0,1</resolveGoods>
		<coin>2,200,300</coin>
	</T>
	<T>
		<Id>10</Id>
		<quality>2</quality>
		<series>2</series>
		<name>绿色二阶</name>
		<goods>1030</goods>
		<value>8</value>
		<resolveGoods>1000,1030,0,1</resolveGoods>
		<coin>2,400,600</coin>
	</T>
	<T>
		<Id>11</Id>
		<quality>3</quality>
		<series>2</series>
		<name>蓝色二阶</name>
		<goods>1030</goods>
		<value>15</value>
		<resolveGoods>1000,1030,0,1</resolveGoods>
		<coin>2,600,900</coin>
	</T>
	<T>
		<Id>12</Id>
		<quality>4</quality>
		<series>2</series>
		<name>紫色二阶</name>
		<goods>1030</goods>
		<value>25</value>
		<resolveGoods>1000,1030,0,1</resolveGoods>
		<coin>2,1000,1500</coin>
	</T>
	<T>
		<Id>13</Id>
		<quality>5</quality>
		<series>2</series>
		<name>橙色二阶</name>
		<goods>1030</goods>
		<value>42</value>
		<resolveGoods>1000,1030,0,1</resolveGoods>
		<coin>2,1600,2400</coin>
	</T>
	<T>
		<Id>14</Id>
		<quality>6</quality>
		<series>2</series>
		<name>金色二阶</name>
		<goods>1030</goods>
		<value>75</value>
		<resolveGoods>1000,1030,0,1</resolveGoods>
		<coin>2,2000,3000</coin>
	</T>
	<T>
		<Id>15</Id>
		<quality>7</quality>
		<series>2</series>
		<name>粉色二阶</name>
		<goods>1030</goods>
		<value>130</value>
		<resolveGoods>1000,1030,0,1</resolveGoods>
		<coin>2,2400,3600</coin>
	</T>
	<T>
		<Id>16</Id>
		<quality>8</quality>
		<series>2</series>
		<name>红色二阶</name>
		<goods>1030</goods>
		<value>225</value>
		<resolveGoods>1000,1030,0,1</resolveGoods>
		<coin>2,3000,4500</coin>
	</T>
	<T>
		<Id>17</Id>
		<quality>1</quality>
		<series>3</series>
		<name>白色三阶</name>
		<goods>1030</goods>
		<value>6</value>
		<resolveGoods>1000,1030,0,1</resolveGoods>
		<coin>2,200,300</coin>
	</T>
	<T>
		<Id>18</Id>
		<quality>2</quality>
		<series>3</series>
		<name>绿色三阶</name>
		<goods>1030</goods>
		<value>10</value>
		<resolveGoods>1000,1030,0,1</resolveGoods>
		<coin>2,400,600</coin>
	</T>
	<T>
		<Id>19</Id>
		<quality>3</quality>
		<series>3</series>
		<name>蓝色三阶</name>
		<goods>1030</goods>
		<value>18</value>
		<resolveGoods>1000,1030,0,1</resolveGoods>
		<coin>2,800,1200</coin>
	</T>
	<T>
		<Id>20</Id>
		<quality>4</quality>
		<series>3</series>
		<name>紫色三阶</name>
		<goods>1030</goods>
		<value>32</value>
		<resolveGoods>1000,1030,0,1</resolveGoods>
		<coin>2,1200,1800</coin>
	</T>
	<T>
		<Id>21</Id>
		<quality>5</quality>
		<series>3</series>
		<name>橙色三阶</name>
		<goods>1030</goods>
		<value>56</value>
		<resolveGoods>1000,1030,0,1</resolveGoods>
		<coin>2,2000,3000</coin>
	</T>
	<T>
		<Id>22</Id>
		<quality>6</quality>
		<series>3</series>
		<name>金色三阶</name>
		<goods>1030</goods>
		<value>96</value>
		<resolveGoods>1000,1030,0,1</resolveGoods>
		<coin>2,2400,3600</coin>
	</T>
	<T>
		<Id>23</Id>
		<quality>7</quality>
		<series>3</series>
		<name>粉色三阶</name>
		<goods>1030</goods>
		<value>170</value>
		<resolveGoods>1000,1030,0,1</resolveGoods>
		<coin>2,3000,4500</coin>
	</T>
	<T>
		<Id>24</Id>
		<quality>8</quality>
		<series>3</series>
		<name>红色三阶</name>
		<goods>1030</goods>
		<value>300</value>
		<resolveGoods>1000,1030,0,1</resolveGoods>
		<coin>2,3600,5400</coin>
	</T>
	<T>
		<Id>25</Id>
		<quality>1</quality>
		<series>4</series>
		<name>白色四阶</name>
		<goods>1030</goods>
		<value>7</value>
		<resolveGoods>1000,1030,0,1</resolveGoods>
		<coin>2,400,600</coin>
	</T>
	<T>
		<Id>26</Id>
		<quality>2</quality>
		<series>4</series>
		<name>绿色四阶</name>
		<goods>1030</goods>
		<value>12</value>
		<resolveGoods>1000,1030,0,1</resolveGoods>
		<coin>2,600,900</coin>
	</T>
	<T>
		<Id>27</Id>
		<quality>3</quality>
		<series>4</series>
		<name>蓝色四阶</name>
		<goods>1030</goods>
		<value>22</value>
		<resolveGoods>1000,1030,0,1</resolveGoods>
		<coin>2,1000,1500</coin>
	</T>
	<T>
		<Id>28</Id>
		<quality>4</quality>
		<series>4</series>
		<name>紫色四阶</name>
		<goods>1030</goods>
		<value>40</value>
		<resolveGoods>1000,1030,0,1</resolveGoods>
		<coin>2,1600,2400</coin>
	</T>
	<T>
		<Id>29</Id>
		<quality>5</quality>
		<series>4</series>
		<name>橙色四阶</name>
		<goods>1030</goods>
		<value>70</value>
		<resolveGoods>1000,1030,0,1</resolveGoods>
		<coin>2,2400,3600</coin>
	</T>
	<T>
		<Id>30</Id>
		<quality>6</quality>
		<series>4</series>
		<name>金色四阶</name>
		<goods>1030</goods>
		<value>120</value>
		<resolveGoods>1000,1030,0,1</resolveGoods>
		<coin>2,3000,4500</coin>
	</T>
	<T>
		<Id>31</Id>
		<quality>7</quality>
		<series>4</series>
		<name>粉色四阶</name>
		<goods>1030</goods>
		<value>210</value>
		<resolveGoods>1000,1030,0,1</resolveGoods>
		<coin>2,3600,5400</coin>
	</T>
	<T>
		<Id>32</Id>
		<quality>8</quality>
		<series>4</series>
		<name>红色四阶</name>
		<goods>1030</goods>
		<value>370</value>
		<resolveGoods>1000,1030,0,1</resolveGoods>
		<coin>2,4000,6000</coin>
	</T>
	<T>
		<Id>33</Id>
		<quality>1</quality>
		<series>5</series>
		<name>白色五阶</name>
		<goods>1030</goods>
		<value>9</value>
		<resolveGoods>1000,1030,0,1</resolveGoods>
		<coin>2,400,600</coin>
	</T>
	<T>
		<Id>34</Id>
		<quality>2</quality>
		<series>5</series>
		<name>绿色五阶</name>
		<goods>1030</goods>
		<value>15</value>
		<resolveGoods>1000,1030,0,1</resolveGoods>
		<coin>2,800,1200</coin>
	</T>
	<T>
		<Id>35</Id>
		<quality>3</quality>
		<series>5</series>
		<name>蓝色五阶</name>
		<goods>1030</goods>
		<value>27</value>
		<resolveGoods>1000,1030,0,1</resolveGoods>
		<coin>2,1200,1800</coin>
	</T>
	<T>
		<Id>36</Id>
		<quality>4</quality>
		<series>5</series>
		<name>紫色五阶</name>
		<goods>1030</goods>
		<value>45</value>
		<resolveGoods>1000,1030,0,1</resolveGoods>
		<coin>2,2000,3000</coin>
	</T>
	<T>
		<Id>37</Id>
		<quality>5</quality>
		<series>5</series>
		<name>橙色五阶</name>
		<goods>1030</goods>
		<value>80</value>
		<resolveGoods>1000,1030,0,1</resolveGoods>
		<coin>2,2800,4200</coin>
	</T>
	<T>
		<Id>38</Id>
		<quality>6</quality>
		<series>5</series>
		<name>金色五阶</name>
		<goods>1030</goods>
		<value>145</value>
		<resolveGoods>1000,1030,0,1</resolveGoods>
		<coin>2,3600,5400</coin>
	</T>
	<T>
		<Id>39</Id>
		<quality>7</quality>
		<series>5</series>
		<name>粉色五阶</name>
		<goods>1030</goods>
		<value>250</value>
		<resolveGoods>1000,1030,0,1</resolveGoods>
		<coin>2,4000,6000</coin>
	</T>
	<T>
		<Id>40</Id>
		<quality>8</quality>
		<series>5</series>
		<name>红色五阶</name>
		<goods>1030</goods>
		<value>440</value>
		<resolveGoods>1000,1030,0,1</resolveGoods>
		<coin>2,4400,6600</coin>
	</T>
	<T>
		<Id>41</Id>
		<quality>1</quality>
		<series>6</series>
		<name>白色六阶</name>
		<goods>1030</goods>
		<value>10</value>
		<resolveGoods>1000,1030,0,1</resolveGoods>
		<coin>2,600,900</coin>
	</T>
	<T>
		<Id>42</Id>
		<quality>2</quality>
		<series>6</series>
		<name>绿色六阶</name>
		<goods>1030</goods>
		<value>18</value>
		<resolveGoods>1000,1030,0,1</resolveGoods>
		<coin>2,1000,1500</coin>
	</T>
	<T>
		<Id>43</Id>
		<quality>3</quality>
		<series>6</series>
		<name>蓝色六阶</name>
		<goods>1030</goods>
		<value>30</value>
		<resolveGoods>1000,1030,0,1</resolveGoods>
		<coin>2,1600,2400</coin>
	</T>
	<T>
		<Id>44</Id>
		<quality>4</quality>
		<series>6</series>
		<name>紫色六阶</name>
		<goods>1030</goods>
		<value>54</value>
		<resolveGoods>1000,1030,0,1</resolveGoods>
		<coin>2,2400,3600</coin>
	</T>
	<T>
		<Id>45</Id>
		<quality>5</quality>
		<series>6</series>
		<name>橙色六阶</name>
		<goods>1030</goods>
		<value>95</value>
		<resolveGoods>1000,1030,0,1</resolveGoods>
		<coin>2,3200,4800</coin>
	</T>
	<T>
		<Id>46</Id>
		<quality>6</quality>
		<series>6</series>
		<name>金色六阶</name>
		<goods>1030</goods>
		<value>165</value>
		<resolveGoods>1000,1030,0,1</resolveGoods>
		<coin>2,4000,6000</coin>
	</T>
	<T>
		<Id>47</Id>
		<quality>7</quality>
		<series>6</series>
		<name>粉色六阶</name>
		<goods>1030</goods>
		<value>290</value>
		<resolveGoods>1000,1030,0,1</resolveGoods>
		<coin>2,4400,6600</coin>
	</T>
	<T>
		<Id>48</Id>
		<quality>8</quality>
		<series>6</series>
		<name>红色六阶</name>
		<goods>1030</goods>
		<value>510</value>
		<resolveGoods>1000,1030,0,1</resolveGoods>
		<coin>2,5000,7500</coin>
	</T>
	<T>
		<Id>49</Id>
		<quality>1</quality>
		<series>7</series>
		<name>白色七阶</name>
		<goods>1030</goods>
		<value>12</value>
		<resolveGoods>1000,1030,0,1</resolveGoods>
		<coin>2,800,1200</coin>
	</T>
	<T>
		<Id>50</Id>
		<quality>2</quality>
		<series>7</series>
		<name>绿色七阶</name>
		<goods>1030</goods>
		<value>20</value>
		<resolveGoods>1000,1030,0,1</resolveGoods>
		<coin>2,1200,1800</coin>
	</T>
	<T>
		<Id>51</Id>
		<quality>3</quality>
		<series>7</series>
		<name>蓝色七阶</name>
		<goods>1030</goods>
		<value>35</value>
		<resolveGoods>1000,1030,0,1</resolveGoods>
		<coin>2,2000,3000</coin>
	</T>
	<T>
		<Id>52</Id>
		<quality>4</quality>
		<series>7</series>
		<name>紫色七阶</name>
		<goods>1030</goods>
		<value>60</value>
		<resolveGoods>1000,1030,0,1</resolveGoods>
		<coin>2,3000,4500</coin>
	</T>
	<T>
		<Id>53</Id>
		<quality>5</quality>
		<series>7</series>
		<name>橙色七阶</name>
		<goods>1030</goods>
		<value>108</value>
		<resolveGoods>1000,1030,0,1</resolveGoods>
		<coin>2,4000,6000</coin>
	</T>
	<T>
		<Id>54</Id>
		<quality>6</quality>
		<series>7</series>
		<name>金色七阶</name>
		<goods>1030</goods>
		<value>190</value>
		<resolveGoods>1000,1030,0,1</resolveGoods>
		<coin>2,4400,6600</coin>
	</T>
	<T>
		<Id>55</Id>
		<quality>7</quality>
		<series>7</series>
		<name>粉色七阶</name>
		<goods>1030</goods>
		<value>330</value>
		<resolveGoods>1000,1030,0,1</resolveGoods>
		<coin>2,5000,7500</coin>
	</T>
	<T>
		<Id>56</Id>
		<quality>8</quality>
		<series>7</series>
		<name>红色七阶</name>
		<goods>1030</goods>
		<value>580</value>
		<resolveGoods>1000,1030,0,1</resolveGoods>
		<coin>2,5600,8400</coin>
	</T>
	<T>
		<Id>57</Id>
		<quality>1</quality>
		<series>8</series>
		<name>白色八阶</name>
		<goods>1030</goods>
		<value>14</value>
		<resolveGoods>1000,1030,0,1</resolveGoods>
		<coin>2,1000,1500</coin>
	</T>
	<T>
		<Id>58</Id>
		<quality>2</quality>
		<series>8</series>
		<name>绿色八阶</name>
		<goods>1030</goods>
		<value>24</value>
		<resolveGoods>1000,1030,0,1</resolveGoods>
		<coin>2,1600,2400</coin>
	</T>
	<T>
		<Id>59</Id>
		<quality>3</quality>
		<series>8</series>
		<name>蓝色八阶</name>
		<goods>1030</goods>
		<value>40</value>
		<resolveGoods>1000,1030,0,1</resolveGoods>
		<coin>2,2400,3600</coin>
	</T>
	<T>
		<Id>60</Id>
		<quality>4</quality>
		<series>8</series>
		<name>紫色八阶</name>
		<goods>1030</goods>
		<value>70</value>
		<resolveGoods>1000,1030,0,1</resolveGoods>
		<coin>2,3600,5400</coin>
	</T>
	<T>
		<Id>61</Id>
		<quality>5</quality>
		<series>8</series>
		<name>橙色八阶</name>
		<goods>1030</goods>
		<value>120</value>
		<resolveGoods>1000,1030,0,1</resolveGoods>
		<coin>2,4400,6600</coin>
	</T>
	<T>
		<Id>62</Id>
		<quality>6</quality>
		<series>8</series>
		<name>金色八阶</name>
		<goods>1030</goods>
		<value>210</value>
		<resolveGoods>1000,1030,0,1</resolveGoods>
		<coin>2,5000,7500</coin>
	</T>
	<T>
		<Id>63</Id>
		<quality>7</quality>
		<series>8</series>
		<name>粉色八阶</name>
		<goods>1030</goods>
		<value>370</value>
		<resolveGoods>1000,1030,0,1</resolveGoods>
		<coin>2,5600,8400</coin>
	</T>
	<T>
		<Id>64</Id>
		<quality>8</quality>
		<series>8</series>
		<name>红色八阶</name>
		<goods>1030</goods>
		<value>650</value>
		<resolveGoods>1000,1030,0,1</resolveGoods>
		<coin>2,6000,9000</coin>
	</T>
	<T>
		<Id>65</Id>
		<quality>1</quality>
		<series>9</series>
		<name>白色九阶</name>
		<goods>1030</goods>
		<value>15</value>
		<resolveGoods>1000,1030,0,1</resolveGoods>
		<coin>2,1200,1800</coin>
	</T>
	<T>
		<Id>66</Id>
		<quality>2</quality>
		<series>9</series>
		<name>绿色九阶</name>
		<goods>1030</goods>
		<value>25</value>
		<resolveGoods>1000,1030,0,1</resolveGoods>
		<coin>2,2000,3000</coin>
	</T>
	<T>
		<Id>67</Id>
		<quality>3</quality>
		<series>9</series>
		<name>蓝色九阶</name>
		<goods>1030</goods>
		<value>45</value>
		<resolveGoods>1000,1030,0,1</resolveGoods>
		<coin>2,3000,4500</coin>
	</T>
	<T>
		<Id>68</Id>
		<quality>4</quality>
		<series>9</series>
		<name>紫色九阶</name>
		<goods>1030</goods>
		<value>76</value>
		<resolveGoods>1000,1030,0,1</resolveGoods>
		<coin>2,4000,6000</coin>
	</T>
	<T>
		<Id>69</Id>
		<quality>5</quality>
		<series>9</series>
		<name>橙色九阶</name>
		<goods>1030</goods>
		<value>135</value>
		<resolveGoods>1000,1030,0,1</resolveGoods>
		<coin>2,5000,7500</coin>
	</T>
	<T>
		<Id>70</Id>
		<quality>6</quality>
		<series>9</series>
		<name>金色九阶</name>
		<goods>1030</goods>
		<value>235</value>
		<resolveGoods>1000,1030,0,1</resolveGoods>
		<coin>2,5600,8400</coin>
	</T>
	<T>
		<Id>71</Id>
		<quality>7</quality>
		<series>9</series>
		<name>粉色九阶</name>
		<goods>1030</goods>
		<value>410</value>
		<resolveGoods>1000,1030,0,1</resolveGoods>
		<coin>2,6000,9000</coin>
	</T>
	<T>
		<Id>72</Id>
		<quality>8</quality>
		<series>9</series>
		<name>红色九阶</name>
		<goods>1030</goods>
		<value>720</value>
		<resolveGoods>1000,1030,0,1</resolveGoods>
		<coin>2,6400,9600</coin>
	</T>
	<T>
		<Id>73</Id>
		<quality>1</quality>
		<series>10</series>
		<name>白色十阶</name>
		<goods>1030</goods>
		<value>16</value>
		<resolveGoods>1000,1030,0,1</resolveGoods>
		<coin>2,1600,2400</coin>
	</T>
	<T>
		<Id>74</Id>
		<quality>2</quality>
		<series>10</series>
		<name>绿色十阶</name>
		<goods>1030</goods>
		<value>30</value>
		<resolveGoods>1000,1030,0,1</resolveGoods>
		<coin>2,2400,3600</coin>
	</T>
	<T>
		<Id>75</Id>
		<quality>3</quality>
		<series>10</series>
		<name>蓝色十阶</name>
		<goods>1030</goods>
		<value>48</value>
		<resolveGoods>1000,1030,0,1</resolveGoods>
		<coin>2,3600,5400</coin>
	</T>
	<T>
		<Id>76</Id>
		<quality>4</quality>
		<series>10</series>
		<name>紫色十阶</name>
		<goods>1030</goods>
		<value>85</value>
		<resolveGoods>1000,1030,0,1</resolveGoods>
		<coin>2,5000,7500</coin>
	</T>
	<T>
		<Id>77</Id>
		<quality>5</quality>
		<series>10</series>
		<name>橙色十阶</name>
		<goods>1030</goods>
		<value>150</value>
		<resolveGoods>1000,1030,0,1</resolveGoods>
		<coin>2,5600,8400</coin>
	</T>
	<T>
		<Id>78</Id>
		<quality>6</quality>
		<series>10</series>
		<name>金色十阶</name>
		<goods>1030</goods>
		<value>255</value>
		<resolveGoods>1000,1030,0,1</resolveGoods>
		<coin>2,6000,9000</coin>
	</T>
	<T>
		<Id>79</Id>
		<quality>7</quality>
		<series>10</series>
		<name>粉色十阶</name>
		<goods>1030</goods>
		<value>450</value>
		<resolveGoods>1000,1030,0,1</resolveGoods>
		<coin>2,6400,9600</coin>
	</T>
	<T>
		<Id>80</Id>
		<quality>8</quality>
		<series>10</series>
		<name>红色十阶</name>
		<goods>1030</goods>
		<value>785</value>
		<resolveGoods>1000,1030,0,1</resolveGoods>
		<coin>2,7000,10500</coin>
	</T>
</root>